ethoscope/__init__.py
ethoscope/core/__init__.py
ethoscope/core/data_point.py
ethoscope/core/monitor.py
ethoscope/core/roi.py
ethoscope/core/tracking_unit.py
ethoscope/core/variables.py
ethoscope/drawers/__init__.py
ethoscope/drawers/drawers.py
ethoscope/hardware/__init__.py
ethoscope/hardware/input/__init__.py
ethoscope/hardware/input/cameras.py
ethoscope/hardware/interfaces/__init__.py
ethoscope/hardware/interfaces/interfaces.py
ethoscope/hardware/interfaces/lynx_motion.py
ethoscope/hardware/interfaces/odour_delivery_device.py
ethoscope/hardware/interfaces/optomotor.py
ethoscope/hardware/interfaces/serial_wrapper.py
ethoscope/hardware/interfaces/sleep_depriver_interface.py
ethoscope/roi_builders/__init__.py
ethoscope/roi_builders/img_roi_builder.py
ethoscope/roi_builders/roi_builders.py
ethoscope/roi_builders/target_roi_builder.py
ethoscope/stimulators/__init__.py
ethoscope/stimulators/odour_stimulators.py
ethoscope/stimulators/optomotor_stimulators.py
ethoscope/stimulators/sleep_depriver_stimulators.py
ethoscope/stimulators/stimulators.py
ethoscope/tests/__init__.py
ethoscope/trackers/__init__.py
ethoscope/trackers/adaptive_bg_tracker.py
ethoscope/trackers/multi_fly_tracker.py
ethoscope/trackers/single_roi_tracker.py
ethoscope/trackers/trackers.py
ethoscope/utils/__init__.py
ethoscope/utils/debug.py
ethoscope/utils/description.py
ethoscope/utils/img_proc.py
ethoscope/utils/io.py
ethoscope/utils/scheduler.py
ethoscope/web_utils/__init__.py
ethoscope/web_utils/control_thread.py
ethoscope/web_utils/helpers.py
ethoscope/web_utils/record.py
ethoscope_shaferlab-1.0.999.data/scripts/device_server.py
scripts/__init__.py
scripts/device_server.py
ethoscope_shaferlab-1.0.999.dist-info/METADATA
ethoscope_shaferlab-1.0.999.dist-info/WHEEL
ethoscope_shaferlab-1.0.999.dist-info/top_level.txt
ethoscope_shaferlab-1.0.999.dist-info/RECORD
